{"nodes": [{"id": "home_fernpa_cleave_cleave_effects_grit_py", "label": "grit.py", "file_type": "code", "source_file": "cleave/effects/grit.py", "source_location": "L1"}, {"id": "home_fernpa_cleave_cleave_effects_grit_grit_strength", "label": "grit_strength()", "file_type": "code", "source_file": "cleave/effects/grit.py", "source_location": "L22"}, {"id": "home_fernpa_cleave_cleave_effects_grit_aberration_px", "label": "aberration_px()", "file_type": "code", "source_file": "cleave/effects/grit.py", "source_location": "L27"}, {"id": "home_fernpa_cleave_cleave_effects_grit_gritstate", "label": "GritState", "file_type": "code", "source_file": "cleave/effects/grit.py", "source_location": "L33"}, {"id": "home_fernpa_cleave_cleave_effects_grit_gritstate_sample_and_update", "label": ".sample_and_update()", "file_type": "code", "source_file": "cleave/effects/grit.py", "source_location": "L36"}, {"id": "signals", "label": "Signals", "file_type": "code", "source_file": "", "source_location": "", "origin_file": "/home/fernpa/cleave/cleave/effects/grit.py"}, {"id": "effectdef", "label": "EffectDef", "file_type": "code", "source_file": "", "source_location": "", "origin_file": "/home/fernpa/cleave/cleave/effects/grit.py"}, {"id": "home_fernpa_cleave_cleave_effects_grit_update_grit", "label": "_update_grit()", "file_type": "code", "source_file": "cleave/effects/grit.py", "source_location": "L49"}, {"id": "home_fernpa_cleave_cleave_effects_grit_apply_grit", "label": "_apply_grit()", "file_type": "code", "source_file": "cleave/effects/grit.py", "source_location": "L58"}, {"id": "layermodifiers", "label": "LayerModifiers", "file_type": "code", "source_file": "", "source_location": "", "origin_file": "/home/fernpa/cleave/cleave/effects/grit.py"}, {"id": "home_fernpa_cleave_cleave_effects_grit_rationale_1", "label": "Per-layer film grain and chromatic aberration: envelope follow from signals.", "file_type": "rationale", "source_file": "cleave/effects/grit.py", "source_location": "L1"}], "edges": [{"source": "home_fernpa_cleave_cleave_effects_grit_py", "target": "dataclasses", "relation": "imports_from", "context": "import", "confidence": "EXTRACTED", "source_file": "cleave/effects/grit.py", "source_location": "L5", "weight": 1.0}, {"source": "home_fernpa_cleave_cleave_effects_grit_py", "target": "typing", "relation": "imports_from", "context": "import", "confidence": "EXTRACTED", "source_file": "cleave/effects/grit.py", "source_location": "L6", "weight": 1.0}, {"source": "home_fernpa_cleave_cleave_effects_grit_py", "target": "cleave_effects_constants", "relation": "imports_from", "context": "import", "confidence": "EXTRACTED", "source_file": "cleave/effects/grit.py", "source_location": "L8", "weight": 1.0}, {"source": "home_fernpa_cleave_cleave_effects_grit_py", "target": "cleave_effects_handlers", "relation": "imports_from", "context": "import", "confidence": "EXTRACTED", "source_file": "cleave/effects/grit.py", "source_location": "L9", "weight": 1.0}, {"source": "home_fernpa_cleave_cleave_effects_grit_py", "target": "cleave_effects_pulse", "relation": "imports_from", "context": "import", "confidence": "EXTRACTED", "source_file": "cleave/effects/grit.py", "source_location": "L10", "weight": 1.0}, {"source": "home_fernpa_cleave_cleave_effects_grit_py", "target": "cleave_effects_registry", "relation": "imports_from", "context": "import", "confidence": "EXTRACTED", "source_file": "cleave/effects/grit.py", "source_location": "L11", "weight": 1.0}, {"source": "home_fernpa_cleave_cleave_effects_grit_py", "target": "cleave_effects_sampling", "relation": "imports_from", "context": "import", "confidence": "EXTRACTED", "source_file": "cleave/effects/grit.py", "source_location": "L12", "weight": 1.0}, {"source": "home_fernpa_cleave_cleave_effects_grit_py", "target": "cleave_signals", "relation": "imports_from", "context": "import", "confidence": "EXTRACTED", "source_file": "cleave/effects/grit.py", "source_location": "L13", "weight": 1.0}, {"source": "home_fernpa_cleave_cleave_effects_grit_py", "target": "cleave_effects_runtime", "relation": "imports_from", "context": "import", "confidence": "EXTRACTED", "source_file": "cleave/effects/grit.py", "source_location": "L16", "weight": 1.0}, {"source": "home_fernpa_cleave_cleave_effects_grit_py", "target": "home_fernpa_cleave_cleave_effects_grit_grit_strength", "relation": "contains", "confidence": "EXTRACTED", "source_file": "cleave/effects/grit.py", "source_location": "L22", "weight": 1.0}, {"source": "home_fernpa_cleave_cleave_effects_grit_py", "target": "home_fernpa_cleave_cleave_effects_grit_aberration_px", "relation": "contains", "confidence": "EXTRACTED", "source_file": "cleave/effects/grit.py", "source_location": "L27", "weight": 1.0}, {"source": "home_fernpa_cleave_cleave_effects_grit_py", "target": "home_fernpa_cleave_cleave_effects_grit_gritstate", "relation": "contains", "confidence": "EXTRACTED", "source_file": "cleave/effects/grit.py", "source_location": "L33", "weight": 1.0}, {"source": "home_fernpa_cleave_cleave_effects_grit_gritstate", "target": "home_fernpa_cleave_cleave_effects_grit_gritstate_sample_and_update", "relation": "method", "confidence": "EXTRACTED", "source_file": "cleave/effects/grit.py", "source_location": "L36", "weight": 1.0}, {"source": "home_fernpa_cleave_cleave_effects_grit_gritstate_sample_and_update", "target": "signals", "relation": "references", "context": "parameter_type", "confidence": "EXTRACTED", "source_file": "cleave/effects/grit.py", "source_location": "L36", "weight": 1.0}, {"source": "home_fernpa_cleave_cleave_effects_grit_gritstate_sample_and_update", "target": "effectdef", "relation": "references", "context": "parameter_type", "confidence": "EXTRACTED", "source_file": "cleave/effects/grit.py", "source_location": "L36", "weight": 1.0}, {"source": "home_fernpa_cleave_cleave_effects_grit_py", "target": "home_fernpa_cleave_cleave_effects_grit_update_grit", "relation": "contains", "confidence": "EXTRACTED", "source_file": "cleave/effects/grit.py", "source_location": "L49", "weight": 1.0}, {"source": "home_fernpa_cleave_cleave_effects_grit_update_grit", "target": "home_fernpa_cleave_cleave_effects_grit_gritstate", "relation": "references", "context": "parameter_type", "confidence": "EXTRACTED", "source_file": "cleave/effects/grit.py", "source_location": "L49", "weight": 1.0}, {"source": "home_fernpa_cleave_cleave_effects_grit_update_grit", "target": "signals", "relation": "references", "context": "parameter_type", "confidence": "EXTRACTED", "source_file": "cleave/effects/grit.py", "source_location": "L49", "weight": 1.0}, {"source": "home_fernpa_cleave_cleave_effects_grit_update_grit", "target": "effectdef", "relation": "references", "context": "parameter_type", "confidence": "EXTRACTED", "source_file": "cleave/effects/grit.py", "source_location": "L49", "weight": 1.0}, {"source": "home_fernpa_cleave_cleave_effects_grit_py", "target": "home_fernpa_cleave_cleave_effects_grit_apply_grit", "relation": "contains", "confidence": "EXTRACTED", "source_file": "cleave/effects/grit.py", "source_location": "L58", "weight": 1.0}, {"source": "home_fernpa_cleave_cleave_effects_grit_apply_grit", "target": "layermodifiers", "relation": "references", "context": "parameter_type", "confidence": "EXTRACTED", "source_file": "cleave/effects/grit.py", "source_location": "L58", "weight": 1.0}, {"source": "home_fernpa_cleave_cleave_effects_grit_apply_grit", "target": "home_fernpa_cleave_cleave_effects_grit_gritstate", "relation": "references", "context": "parameter_type", "confidence": "EXTRACTED", "source_file": "cleave/effects/grit.py", "source_location": "L58", "weight": 1.0}, {"source": "home_fernpa_cleave_cleave_effects_grit_apply_grit", "target": "layermodifiers", "relation": "references", "context": "return_type", "confidence": "EXTRACTED", "source_file": "cleave/effects/grit.py", "source_location": "L58", "weight": 1.0}, {"source": "home_fernpa_cleave_cleave_effects_grit_update_grit", "target": "home_fernpa_cleave_cleave_effects_grit_gritstate_sample_and_update", "relation": "calls", "context": "call", "confidence": "EXTRACTED", "source_file": "cleave/effects/grit.py", "source_location": "L55", "weight": 1.0}, {"source": "home_fernpa_cleave_cleave_effects_grit_apply_grit", "target": "home_fernpa_cleave_cleave_effects_grit_grit_strength", "relation": "calls", "context": "call", "confidence": "EXTRACTED", "source_file": "cleave/effects/grit.py", "source_location": "L60", "weight": 1.0}, {"source": "home_fernpa_cleave_cleave_effects_grit_apply_grit", "target": "home_fernpa_cleave_cleave_effects_grit_aberration_px", "relation": "calls", "context": "call", "confidence": "EXTRACTED", "source_file": "cleave/effects/grit.py", "source_location": "L63", "weight": 1.0}, {"source": "home_fernpa_cleave_cleave_effects_grit_rationale_1", "target": "home_fernpa_cleave_cleave_effects_grit_py", "relation": "rationale_for", "confidence": "EXTRACTED", "source_file": "cleave/effects/grit.py", "source_location": "L1", "weight": 1.0}], "raw_calls": [{"caller_nid": "home_fernpa_cleave_cleave_effects_grit_grit_strength", "callee": "clamp_effect_pct", "is_member_call": false, "source_file": "/home/fernpa/cleave/cleave/effects/grit.py", "source_location": "L23", "receiver": null}, {"caller_nid": "home_fernpa_cleave_cleave_effects_grit_aberration_px", "callee": "clamp_effect_pct", "is_member_call": false, "source_file": "/home/fernpa/cleave/cleave/effects/grit.py", "source_location": "L28", "receiver": null}, {"caller_nid": "home_fernpa_cleave_cleave_effects_grit_gritstate_sample_and_update", "callee": "sample_normalized", "is_member_call": false, "source_file": "/home/fernpa/cleave/cleave/effects/grit.py", "source_location": "L42", "receiver": null}, {"caller_nid": "home_fernpa_cleave_cleave_effects_grit_gritstate_sample_and_update", "callee": "update_envelope", "is_member_call": false, "source_file": "/home/fernpa/cleave/cleave/effects/grit.py", "source_location": "L43", "receiver": null}]}